

[
  {
    "id": "1111",
    "url": "https://drive.google.com/uc?export=download&id=1AjPwylDJgR8DOnmJWeRgZzjsohi-7ekj",
    "title": "Longing",
    "artist": "David Chavez",
    "artwork": "https://picsum.photos/200",
    "content": "Contrary to popular belief, Lorem Ipsum is not simply random text. It has roots in a piece of classical Latin literature from 45 BC, making it over 2000 years old. Richard McClintock, a Latin ",
    "styles": {
      "color": "white",
      "fontFamily": "Blokletters-Potlood",
      "textAlign": "justify",
      "width": "70%",
      "fontWeight": "800" 
    }
  },
  {
    "id": "2222",
    "url": "https://drive.google.com/uc?export=download&id=1VM9_umeyzJn0v1pRzR1BSm9y3IhZ3c0E",
    "title": "Soul Searching (Demo)",
    "artist": "David Chavez",
    "artwork": "https://placeimg.com/640/640/nature",
    "content": "It is a long established fact that a reader will be distracted by the readable content of a page when looking at its layout. The point of using Lorem Ipsum is that it has a more-or-less normal distribution of letters, as opposed to using C",
    "styles": {
      "color": "white",
      "fontFamily": "Blokletters-Potlood",
      "textAlign": "justify",
      "width": "70%",
      "fontStyle": "italic","fontWeight": "700" 
    }
  },
  {
    "id": "3333",
    "url": "https://drive.google.com/uc?export=download&id=1bmvPOy2IVbkUROgm0dqiZry_miiL4OqI",
    "title": "Lullaby (Demo)",
    "artist": "David Chavez",
    "artwork": "https://placeimg.com/640/640/people",
    "content": " The point of using Lorem Ipsum is that it has a more-or-less normal distribution of letters, as opposed to using C",
    "styles": {
      "color": "white",
      "fontFamily": "Blokletters-Potlood",
      "textAlign": "justify",
      "width": "70%",
      "fontStyle": "italic","fontWeight": "700" 
    }
  },
  {
    "id": "4444",
    "url": "https://drive.google.com/uc?export=download&id=1V-c_WmanMA9i5BwfkmTs-605BQDsfyzC",
    "title": "Rhythm City (Demo)",
    "artist": "David Chavez",
    "artwork": "https://placeimg.com/640/640/beer",
    "content": "looking at its layout. The point of using Lorem Ipsum is that it has a more-or-less normal distribution of letters, as opposed to using C",
    "styles": {
      "color": "white",
      "fontFamily": "Blokletters-Potlood",
      "textAlign": "justify",
      "width": "70%",
      "fontStyle": "italic","fontWeight": "700" 
    }
  }
]